lightprop2d/__init__.py
lightprop2d/beam2d.py
lightprop2d/profiles.py
lightprop2d-1.0.4.dist-info/LICENSE
lightprop2d-1.0.4.dist-info/METADATA
lightprop2d-1.0.4.dist-info/WHEEL
lightprop2d-1.0.4.dist-info/top_level.txt
lightprop2d-1.0.4.dist-info/RECORD
