Metadata-Version: 2.1
Name: lightprop2d
Version: 1.0.4
Summary: Light propagation in free space with fourier transform
Home-page: https://github.com/vongostev/lightprop2d
Author: Pavel Gostev
Author-email: gostev.pavel@physics.msu.ru
Classifier: Programming Language :: Python :: 3
Classifier: License :: OSI Approved :: MIT License
Classifier: Operating System :: OS Independent
Requires-Python: >=3.6
License-File: LICENSE
Requires-Dist: numpy
Requires-Dist: scipy
